COPYRIGHT.txt
README.rst
setup.py
src/ScreenCapLibrary/ScreenCapLibrary.py
src/ScreenCapLibrary/__init__.py
src/ScreenCapLibrary/pygtk.py
src/ScreenCapLibrary/version.py
src/robotframework_screencaplibrary.egg-info/PKG-INFO
src/robotframework_screencaplibrary.egg-info/SOURCES.txt
src/robotframework_screencaplibrary.egg-info/dependency_links.txt
src/robotframework_screencaplibrary.egg-info/requires.txt
src/robotframework_screencaplibrary.egg-info/top_level.txt